datastruct/__init__.py
datastruct/adapters/__init__.py
datastruct/adapters/misc.py
datastruct/adapters/network.py
datastruct/adapters/time.py
datastruct/fields/__init__.py
datastruct/fields/_utils.py
datastruct/fields/helper.py
datastruct/fields/special.py
datastruct/fields/standard.py
datastruct/fields/wrapper.py
datastruct/main.py
datastruct/types.py
datastruct/utils/__init__.py
datastruct/utils/config.py
datastruct/utils/const.py
datastruct/utils/context.py
datastruct/utils/fields.py
datastruct/utils/fmt.py
datastruct/utils/misc.py
datastruct/utils/public.py
py_datastruct-1.1.0.dist-info/LICENSE
py_datastruct-1.1.0.dist-info/METADATA
py_datastruct-1.1.0.dist-info/WHEEL
py_datastruct-1.1.0.dist-info/RECORD
