Metadata-Version: 2.1
Name: py-datastruct
Version: 1.1.0
Summary: Combination of struct and dataclasses for easy parsing of binary formats
License: MIT
Author: Kuba Szczodrzyński
Author-email: kuba@szczodrzynski.pl
Requires-Python: >=3.7,<4.0
Classifier: License :: OSI Approved :: MIT License
Classifier: Programming Language :: Python :: 3
Classifier: Programming Language :: Python :: 3.7
Classifier: Programming Language :: Python :: 3.8
Classifier: Programming Language :: Python :: 3.9
Classifier: Programming Language :: Python :: 3.10
Classifier: Programming Language :: Python :: 3.11
Classifier: Programming Language :: Python :: 3.12
